dexo/__init__.py
dexo/__main__.py
dexo-3.4.dist-info/LICENSE
dexo-3.4.dist-info/METADATA
dexo-3.4.dist-info/WHEEL
dexo-3.4.dist-info/entry_points.txt
dexo-3.4.dist-info/top_level.txt
dexo-3.4.dist-info/RECORD
