Metadata-Version: 2.1
Name: dexo
Version: 3.4
Summary: A cli for a quick and easy web dev kit
Home-page: https://github.com/kavinbharathii/dexo
Author: Kavin Bharathi
Author-email: r.m.kavinbharathi@gmail.com
Requires-Python: >=3.5
License-File: LICENSE
Requires-Dist: rich (>=12.5.1)
